jdmn/version.py
jdmn/feel/lib/BaseFEELLib.py
jdmn/feel/lib/BaseStandardFEELLib.py
jdmn/feel/lib/DefaultStandardFEELLib.py
jdmn/feel/lib/FEELLib.py
jdmn/feel/lib/Types.py
jdmn/feel/lib/Utils.py
jdmn/feel/lib/type/BaseType.py
jdmn/feel/lib/type/ComparableComparator.py
jdmn/feel/lib/type/EqualityComparator.py
jdmn/feel/lib/type/RelationalComparator.py
jdmn/feel/lib/type/bool/DefaultBooleanLib.py
jdmn/feel/lib/type/bool/DefaultBooleanType.py
jdmn/feel/lib/type/bool/TernaryBooleanLogicUtil.py
jdmn/feel/lib/type/context/DefaultContextType.py
jdmn/feel/lib/type/function/DefaultFunctionType.py
jdmn/feel/lib/type/list/DefaultListLib.py
jdmn/feel/lib/type/list/DefaultListType.py
jdmn/feel/lib/type/numeric/DefaultNumericLib.py
jdmn/feel/lib/type/numeric/DefaultNumericType.py
jdmn/feel/lib/type/numeric/NumericComparator.py
jdmn/feel/lib/type/range/DefaultRangeLib.py
jdmn/feel/lib/type/range/DefaultRangeType.py
jdmn/feel/lib/type/string/DefaultStringLib.py
jdmn/feel/lib/type/string/DefaultStringType.py
jdmn/feel/lib/type/string/StringComparator.py
jdmn/feel/lib/type/time/BaseDateTimeComparator.py
jdmn/feel/lib/type/time/DefaultBaseDateTimeComparator.py
jdmn/feel/lib/type/time/DefaultCalendarType.py
jdmn/feel/lib/type/time/DefaultDateComparator.py
jdmn/feel/lib/type/time/DefaultDateTimeComparator.py
jdmn/feel/lib/type/time/DefaultDateTimeLib.py
jdmn/feel/lib/type/time/DefaultDateTimeType.py
jdmn/feel/lib/type/time/DefaultDateType.py
jdmn/feel/lib/type/time/DefaultDurationComparator.py
jdmn/feel/lib/type/time/DefaultDurationLib.py
jdmn/feel/lib/type/time/DefaultDurationType.py
jdmn/feel/lib/type/time/DefaultTimeComparator.py
jdmn/feel/lib/type/time/DefaultTimeType.py
jdmn/runtime/Assert.py
jdmn/runtime/Context.py
jdmn/runtime/DMNDecision.py
jdmn/runtime/DMNRuntimeException.py
jdmn/runtime/DMNType.py
jdmn/runtime/DefaultDMNBaseDecision.py
jdmn/runtime/ExecutionContext.py
jdmn/runtime/LambdaExpression.py
jdmn/runtime/LazyEval.py
jdmn/runtime/NumericRoundingMode.py
jdmn_python_runtime-1.0.5.dist-info/LICENSE.txt
jdmn_python_runtime-1.0.5.dist-info/METADATA
jdmn_python_runtime-1.0.5.dist-info/WHEEL
jdmn_python_runtime-1.0.5.dist-info/top_level.txt
jdmn_python_runtime-1.0.5.dist-info/RECORD
