Metadata-Version: 2.2
Name: jdmn-python-runtime
Version: 1.0.5
Summary: jdmn-python-runtime is a library that supports the execution of DMN
Home-page: https://github.com/goldmansachs/jdmn-python-runtime
Author: Octavian Patrascoiu
Author-email: opatrascoiu@yahoo.com
Maintainer: Octavian Patrascoiu
Maintainer-email: opatrascoiu@yahoo.com
License: Apache 2.0
Classifier: Programming Language :: Python
Classifier: Programming Language :: Python :: 3
Requires-Python: >=3.10
License-File: LICENSE.txt
Requires-Dist: isodate
Requires-Dist: python-dateutil
Requires-Dist: tzdata
Requires-Dist: lxml
Requires-Dist: elementpath
